{
	"info": {
		"_postman_id": "ca55b96c-c11a-4174-bea0-70bbd47cbba8",
		"name": "SweetPi Api",
		"schema": "https://schema.getpostman.com/json/collection/v2.1.0/collection.json"
	},
	"item": [
		{
			"name": "leds",
			"request": {
				"auth": {
					"type": "noauth"
				},
				"method": "POST",
				"header": [],
				"body": {
					"mode": "formdata",
					"formdata": [
						{
							"key": "ledModel",
							"value": "{\n    \"Pin\": \"18\",\n    \"LedState\": \"On\"\n  }",
							"type": "text"
						}
					]
				},
				"url": {
					"raw": "http://node1.:5001/leds",
					"protocol": "http",
					"host": [
						"node1",
						""
					],
					"port": "5001",
					"path": [
						"leds"
					]
				}
			},
			"response": []
		},
		{
			"name": "leds (localhost)",
			"request": {
				"auth": {
					"type": "noauth"
				},
				"method": "POST",
				"header": [],
				"body": {
					"mode": "formdata",
					"formdata": [
						{
							"key": "ledModel",
							"value": "{\n    \"Pin\": \"18\",\n    \"State\": \"On\"\n  }",
							"type": "text"
						}
					]
				},
				"url": {
					"raw": "http://localhost.:5001/leds",
					"protocol": "http",
					"host": [
						"localhost",
						""
					],
					"port": "5001",
					"path": [
						"leds"
					]
				}
			},
			"response": []
		},
		{
			"name": "ping",
			"request": {
				"auth": {
					"type": "noauth"
				},
				"method": "GET",
				"header": [],
				"url": {
					"raw": "http://node1.:5001/ping",
					"protocol": "http",
					"host": [
						"node1",
						""
					],
					"port": "5001",
					"path": [
						"ping"
					]
				}
			},
			"response": []
		}
	]
}